pycba_plotly/__init__.py
pycba_plotly/pycba_plotly.py
pycba_plotly-0.0.3.dist-info/LICENSE
pycba_plotly-0.0.3.dist-info/METADATA
pycba_plotly-0.0.3.dist-info/WHEEL
pycba_plotly-0.0.3.dist-info/top_level.txt
pycba_plotly-0.0.3.dist-info/RECORD
